{"config":{"output_file":null,"full_docs":false,"pub_only":false,"reachable_only":false,"distro_crate":false,"signatures":false,"borrow_data":false},"version":"0.19.1","compilation":{"directory":"/Users/ruifreitas/code/aoc/rust/day_1","program":"/Users/ruifreitas/.rustup/toolchains/stable-x86_64-apple-darwin/bin/rls","arguments":[],"output":"/Users/ruifreitas/code/aoc/rust/day_1/target/rls/debug/deps/libsonar-0bbc6eff154ebc87.rmeta"},"prelude":{"crate_id":{"name":"sonar","disambiguator":[40890160472032702,8625991418912712917]},"crate_root":"src","external_crates":[{"file_name":"/Users/ruifreitas/code/aoc/rust/day_1/src/main.rs","num":1,"id":{"name":"std","disambiguator":[7439535968655576646,17420488833649705410]}},{"file_name":"/Users/ruifreitas/code/aoc/rust/day_1/src/main.rs","num":2,"id":{"name":"core","disambiguator":[1949116827220114676,2065912148165510692]}},{"file_name":"/Users/ruifreitas/code/aoc/rust/day_1/src/main.rs","num":3,"id":{"name":"compiler_builtins","disambiguator":[6424123809251651324,10791243255933316672]}},{"file_name":"/Users/ruifreitas/code/aoc/rust/day_1/src/main.rs","num":4,"id":{"name":"rustc_std_workspace_core","disambiguator":[11089070161906179638,2253832597208660558]}},{"file_name":"/Users/ruifreitas/code/aoc/rust/day_1/src/main.rs","num":5,"id":{"name":"alloc","disambiguator":[3666879193032761931,4629784602926728112]}},{"file_name":"/Users/ruifreitas/code/aoc/rust/day_1/src/main.rs","num":6,"id":{"name":"libc","disambiguator":[17557414160303111626,7572947572632644954]}},{"file_name":"/Users/ruifreitas/code/aoc/rust/day_1/src/main.rs","num":7,"id":{"name":"unwind","disambiguator":[915848953387719454,11341216537588130533]}},{"file_name":"/Users/ruifreitas/code/aoc/rust/day_1/src/main.rs","num":8,"id":{"name":"cfg_if","disambiguator":[4285064400235759547,17176111531075018758]}},{"file_name":"/Users/ruifreitas/code/aoc/rust/day_1/src/main.rs","num":9,"id":{"name":"hashbrown","disambiguator":[6997063163517280748,14486342634155193831]}},{"file_name":"/Users/ruifreitas/code/aoc/rust/day_1/src/main.rs","num":10,"id":{"name":"rustc_std_workspace_alloc","disambiguator":[2053070849310045891,9457326657766539472]}},{"file_name":"/Users/ruifreitas/code/aoc/rust/day_1/src/main.rs","num":11,"id":{"name":"rustc_demangle","disambiguator":[16492367081693084488,12081229032515817188]}},{"file_name":"/Users/ruifreitas/code/aoc/rust/day_1/src/main.rs","num":12,"id":{"name":"std_detect","disambiguator":[14000704685499991975,15439018228330051001]}},{"file_name":"/Users/ruifreitas/code/aoc/rust/day_1/src/main.rs","num":13,"id":{"name":"addr2line","disambiguator":[16882152814081891816,2081400005890767566]}},{"file_name":"/Users/ruifreitas/code/aoc/rust/day_1/src/main.rs","num":14,"id":{"name":"gimli","disambiguator":[17412809486977561704,10774188040798205111]}},{"file_name":"/Users/ruifreitas/code/aoc/rust/day_1/src/main.rs","num":15,"id":{"name":"object","disambiguator":[10299009701328497764,8719717191227013711]}},{"file_name":"/Users/ruifreitas/code/aoc/rust/day_1/src/main.rs","num":16,"id":{"name":"panic_unwind","disambiguator":[13564088873543153286,4566579444635585591]}},{"file_name":"/Users/ruifreitas/code/aoc/rust/day_1/src/main.rs","num":17,"id":{"name":"arrayvec","disambiguator":[15956872570187470876,6151365816205618688]}}],"span":{"file_name":"src/main.rs","byte_start":0,"byte_end":1739,"line_start":1,"line_end":68,"column_start":1,"column_end":2}},"imports":[{"kind":"ExternCrate","ref_id":null,"span":{"file_name":"src/main.rs","byte_start":13,"byte_end":21,"line_start":1,"line_end":1,"column_start":14,"column_end":22},"alias_span":null,"name":"arrayvec","value":"","parent":{"krate":0,"index":0}},{"kind":"Use","ref_id":{"krate":17,"index":98},"span":{"file_name":"src/main.rs","byte_start":38,"byte_end":46,"line_start":3,"line_end":3,"column_start":15,"column_end":23},"alias_span":null,"name":"ArrayVec","value":"","parent":{"krate":0,"index":0}},{"kind":"Use","ref_id":{"krate":1,"index":3016},"span":{"file_name":"src/main.rs","byte_start":68,"byte_end":72,"line_start":6,"line_end":6,"column_start":9,"column_end":13},"alias_span":null,"name":"File","value":"","parent":{"krate":0,"index":0}},{"kind":"Use","ref_id":{"krate":1,"index":4357},"span":{"file_name":"src/main.rs","byte_start":83,"byte_end":90,"line_start":7,"line_end":7,"column_start":10,"column_end":17},"alias_span":null,"name":"BufRead","value":"","parent":{"krate":0,"index":0}},{"kind":"Use","ref_id":{"krate":1,"index":3331},"span":{"file_name":"src/main.rs","byte_start":92,"byte_end":101,"line_start":7,"line_end":7,"column_start":19,"column_end":28},"alias_span":null,"name":"BufReader","value":"","parent":{"krate":0,"index":0}},{"kind":"Use","ref_id":{"krate":1,"index":3753},"span":{"file_name":"src/main.rs","byte_start":103,"byte_end":108,"line_start":7,"line_end":7,"column_start":30,"column_end":35},"alias_span":null,"name":"Error","value":"","parent":{"krate":0,"index":0}},{"kind":"Use","ref_id":{"krate":1,"index":10197},"span":{"file_name":"src/main.rs","byte_start":110,"byte_end":119,"line_start":7,"line_end":7,"column_start":37,"column_end":46},"alias_span":null,"name":"ErrorKind","value":"","parent":{"krate":0,"index":0}},{"kind":"Use","ref_id":{"krate":1,"index":6637},"span":{"file_name":"src/main.rs","byte_start":132,"byte_end":136,"line_start":8,"line_end":8,"column_start":11,"column_end":15},"alias_span":null,"name":"Path","value":"","parent":{"krate":0,"index":0}}],"defs":[{"kind":"Mod","id":{"krate":0,"index":0},"span":{"file_name":"src/main.rs","byte_start":0,"byte_end":1739,"line_start":1,"line_end":68,"column_start":1,"column_end":2},"name":"","qualname":"::","value":"src/main.rs","parent":null,"children":[{"krate":0,"index":1},{"krate":0,"index":2},{"krate":0,"index":3},{"krate":0,"index":4},{"krate":0,"index":7},{"krate":0,"index":8},{"krate":0,"index":11},{"krate":0,"index":12},{"krate":0,"index":15},{"krate":0,"index":18},{"krate":0,"index":21},{"krate":0,"index":24},{"krate":0,"index":27},{"krate":0,"index":28},{"krate":0,"index":33},{"krate":0,"index":34}],"decl_id":null,"docs":"","sig":null,"attributes":[]},{"kind":"Function","id":{"krate":0,"index":27},"span":{"file_name":"src/main.rs","byte_start":145,"byte_end":149,"line_start":11,"line_end":11,"column_start":4,"column_end":8},"name":"main","qualname":"::main","value":"fn main()","parent":null,"children":[],"decl_id":null,"docs":"","sig":null,"attributes":[]},{"kind":"Local","id":{"krate":0,"index":268435483},"span":{"file_name":"src/main.rs","byte_start":162,"byte_end":170,"line_start":12,"line_end":12,"column_start":9,"column_end":17},"name":"filepath","qualname":"filepath$HirId { owner: DefId(0:27 ~ sonar[9145]::main), local_id: 8 }","value":"&std::path::Path","parent":null,"children":[],"decl_id":null,"docs":"","sig":null,"attributes":[]},{"kind":"Local","id":{"krate":0,"index":3355443227},"span":{"file_name":"src/main.rs","byte_start":222,"byte_end":227,"line_start":13,"line_end":13,"column_start":9,"column_end":14},"name":"lines","qualname":"lines$HirId { owner: DefId(0:27 ~ sonar[9145]::main), local_id: 19 }","value":"std::vec::Vec<i32>","parent":null,"children":[],"decl_id":null,"docs":"","sig":null,"attributes":[]},{"kind":"Local","id":{"krate":0,"index":939524123},"span":{"file_name":"src/main.rs","byte_start":355,"byte_end":361,"line_start":15,"line_end":15,"column_start":9,"column_end":15},"name":"result","qualname":"result$HirId { owner: DefId(0:27 ~ sonar[9145]::main), local_id: 28 }","value":"i32","parent":null,"children":[],"decl_id":null,"docs":"","sig":null,"attributes":[]},{"kind":"Local","id":{"krate":0,"index":2751463451},"span":{"file_name":"src/main.rs","byte_start":403,"byte_end":409,"line_start":16,"line_end":16,"column_start":9,"column_end":15},"name":"window","qualname":"window$HirId { owner: DefId(0:27 ~ sonar[9145]::main), local_id: 37 }","value":"i32","parent":null,"children":[],"decl_id":null,"docs":"","sig":null,"attributes":[]},{"kind":"Local","id":{"krate":0,"index":1073741852},"span":{"file_name":"src/main.rs","byte_start":503,"byte_end":511,"line_start":21,"line_end":21,"column_start":20,"column_end":28},"name":"filename","qualname":"::lines_from_file::filename","value":"impl AsRef<Path>","parent":null,"children":[],"decl_id":null,"docs":"","sig":null,"attributes":[]},{"kind":"Type","id":{"krate":0,"index":29},"span":{"file_name":"src/main.rs","byte_start":513,"byte_end":529,"line_start":21,"line_end":21,"column_start":30,"column_end":46},"name":"impl AsRef<Path>","qualname":"::lines_from_file::impl AsRef<Path>$HirId { owner: DefId(0:28 ~ sonar[9145]::lines_from_file), local_id: 0 }","value":"","parent":null,"children":[],"decl_id":null,"docs":"","sig":null,"attributes":[]},{"kind":"Function","id":{"krate":0,"index":28},"span":{"file_name":"src/main.rs","byte_start":487,"byte_end":502,"line_start":21,"line_end":21,"column_start":4,"column_end":19},"name":"lines_from_file","qualname":"::lines_from_file","value":"fn lines_from_file<impl AsRef<Path>: AsRef<Path>>(impl AsRef<Path>)\n-> Result<Vec<i32>, Error>","parent":null,"children":[],"decl_id":null,"docs":"","sig":null,"attributes":[]},{"kind":"Local","id":{"krate":0,"index":1879048220},"span":{"file_name":"src/main.rs","byte_start":568,"byte_end":572,"line_start":22,"line_end":22,"column_start":9,"column_end":13},"name":"file","qualname":"file$HirId { owner: DefId(0:28 ~ sonar[9145]::lines_from_file), local_id: 14 }","value":"std::fs::File","parent":null,"children":[],"decl_id":null,"docs":"","sig":null,"attributes":[]},{"kind":"Local","id":{"krate":0,"index":402653212},"span":{"file_name":"src/main.rs","byte_start":628,"byte_end":631,"line_start":23,"line_end":23,"column_start":9,"column_end":12},"name":"buf","qualname":"buf$HirId { owner: DefId(0:28 ~ sonar[9145]::lines_from_file), local_id: 24 }","value":"std::io::BufReader<std::fs::File>","parent":null,"children":[],"decl_id":null,"docs":"","sig":null,"attributes":[]},{"kind":"Local","id":{"krate":0,"index":2214592540},"span":{"file_name":"src/main.rs","byte_start":686,"byte_end":690,"line_start":25,"line_end":25,"column_start":15,"column_end":19},"name":"line","qualname":"$HirId { owner: DefId(0:28 ~ sonar[9145]::lines_from_file), local_id: 63 }::line","value":"std::result::Result<std::string::String, std::io::Error>","parent":null,"children":[],"decl_id":null,"docs":"","sig":null,"attributes":[]},{"kind":"Local","id":{"krate":0,"index":1677721628},"span":{"file_name":"src/main.rs","byte_start":707,"byte_end":708,"line_start":25,"line_end":25,"column_start":36,"column_end":37},"name":"v","qualname":"$HirId { owner: DefId(0:28 ~ sonar[9145]::lines_from_file), local_id: 60 }::v","value":"std::string::String","parent":null,"children":[],"decl_id":null,"docs":"","sig":null,"attributes":[]},{"kind":"Local","id":{"krate":0,"index":3019898908},"span":{"file_name":"src/main.rs","byte_start":729,"byte_end":730,"line_start":25,"line_end":25,"column_start":58,"column_end":59},"name":"e","qualname":"$HirId { owner: DefId(0:28 ~ sonar[9145]::lines_from_file), local_id: 57 }::e","value":"std::num::ParseIntError","parent":null,"children":[],"decl_id":null,"docs":"","sig":null,"attributes":[]},{"kind":"Local","id":{"krate":0,"index":1073741857},"span":{"file_name":"src/main.rs","byte_start":820,"byte_end":826,"line_start":29,"line_end":29,"column_start":26,"column_end":32},"name":"inputs","qualname":"::measurement_increases::inputs","value":"&mut [i32]","parent":null,"children":[],"decl_id":null,"docs":"","sig":null,"attributes":[]},{"kind":"Function","id":{"krate":0,"index":33},"span":{"file_name":"src/main.rs","byte_start":798,"byte_end":819,"line_start":29,"line_end":29,"column_start":4,"column_end":25},"name":"measurement_increases","qualname":"::measurement_increases","value":"fn measurement_increases(&mut [i32]) -> i32","parent":null,"children":[],"decl_id":null,"docs":"","sig":null,"attributes":[]},{"kind":"Local","id":{"krate":0,"index":2684354593},"span":{"file_name":"src/main.rs","byte_start":861,"byte_end":868,"line_start":30,"line_end":30,"column_start":13,"column_end":20},"name":"counter","qualname":"counter$HirId { owner: DefId(0:33 ~ sonar[9145]::measurement_increases), local_id: 5 }","value":"i32","parent":null,"children":[],"decl_id":null,"docs":"","sig":null,"attributes":[]},{"kind":"Local","id":{"krate":0,"index":3623878689},"span":{"file_name":"src/main.rs","byte_start":888,"byte_end":903,"line_start":32,"line_end":32,"column_start":14,"column_end":29},"name":"iter","qualname":"iter$HirId { owner: DefId(0:33 ~ sonar[9145]::measurement_increases), local_id: 27 }","value":"std::ops::Range<usize>","parent":null,"children":[],"decl_id":null,"docs":"","sig":null,"attributes":[]},{"kind":"Local","id":{"krate":0,"index":4026531873},"span":{"file_name":"src/main.rs","byte_start":888,"byte_end":903,"line_start":32,"line_end":32,"column_start":14,"column_end":29},"name":"__next","qualname":"__next$HirId { owner: DefId(0:33 ~ sonar[9145]::measurement_increases), local_id: 15 }","value":"usize","parent":null,"children":[],"decl_id":null,"docs":"","sig":null,"attributes":[]},{"kind":"Local","id":{"krate":0,"index":134217761},"span":{"file_name":"src/main.rs","byte_start":883,"byte_end":884,"line_start":32,"line_end":32,"column_start":9,"column_end":10},"name":"val","qualname":"val$HirId { owner: DefId(0:33 ~ sonar[9145]::measurement_increases), local_id: 16 }","value":"usize","parent":null,"children":[],"decl_id":null,"docs":"","sig":null,"attributes":[]},{"kind":"Local","id":{"krate":0,"index":2751463457},"span":{"file_name":"src/main.rs","byte_start":883,"byte_end":884,"line_start":32,"line_end":32,"column_start":9,"column_end":10},"name":"i","qualname":"i$HirId { owner: DefId(0:33 ~ sonar[9145]::measurement_increases), local_id: 37 }","value":"usize","parent":null,"children":[],"decl_id":null,"docs":"","sig":null,"attributes":[]},{"kind":"Local","id":{"krate":0,"index":1073741858},"span":{"file_name":"src/main.rs","byte_start":1037,"byte_end":1043,"line_start":41,"line_end":41,"column_start":29,"column_end":35},"name":"inputs","qualname":"::sliding_window_increases::inputs","value":"&mut [i32]","parent":null,"children":[],"decl_id":null,"docs":"","sig":null,"attributes":[]},{"kind":"Function","id":{"krate":0,"index":34},"span":{"file_name":"src/main.rs","byte_start":1012,"byte_end":1036,"line_start":41,"line_end":41,"column_start":4,"column_end":28},"name":"sliding_window_increases","qualname":"::sliding_window_increases","value":"fn sliding_window_increases(&mut [i32]) -> i32","parent":null,"children":[],"decl_id":null,"docs":"","sig":null,"attributes":[]},{"kind":"Local","id":{"krate":0,"index":2415919138},"span":{"file_name":"src/main.rs","byte_start":1078,"byte_end":1081,"line_start":42,"line_end":42,"column_start":13,"column_end":16},"name":"vec","qualname":"vec$HirId { owner: DefId(0:34 ~ sonar[9145]::sliding_window_increases), local_id: 9 }","value":"std::vec::Vec<i32>","parent":null,"children":[],"decl_id":null,"docs":"","sig":null,"attributes":[]},{"kind":"Local","id":{"krate":0,"index":2214592546},"span":{"file_name":"src/main.rs","byte_start":1110,"byte_end":1127,"line_start":44,"line_end":44,"column_start":14,"column_end":31},"name":"iter","qualname":"iter$HirId { owner: DefId(0:34 ~ sonar[9145]::sliding_window_increases), local_id: 33 }","value":"std::ops::Range<usize>","parent":null,"children":[],"decl_id":null,"docs":"","sig":null,"attributes":[]},{"kind":"Local","id":{"krate":0,"index":2818572322},"span":{"file_name":"src/main.rs","byte_start":1110,"byte_end":1127,"line_start":44,"line_end":44,"column_start":14,"column_end":31},"name":"__next","qualname":"__next$HirId { owner: DefId(0:34 ~ sonar[9145]::sliding_window_increases), local_id: 21 }","value":"usize","parent":null,"children":[],"decl_id":null,"docs":"","sig":null,"attributes":[]},{"kind":"Local","id":{"krate":0,"index":1744830498},"span":{"file_name":"src/main.rs","byte_start":1105,"byte_end":1106,"line_start":44,"line_end":44,"column_start":9,"column_end":10},"name":"val","qualname":"val$HirId { owner: DefId(0:34 ~ sonar[9145]::sliding_window_increases), local_id: 22 }","value":"usize","parent":null,"children":[],"decl_id":null,"docs":"","sig":null,"attributes":[]},{"kind":"Local","id":{"krate":0,"index":3556769826},"span":{"file_name":"src/main.rs","byte_start":1105,"byte_end":1106,"line_start":44,"line_end":44,"column_start":9,"column_end":10},"name":"i","qualname":"i$HirId { owner: DefId(0:34 ~ sonar[9145]::sliding_window_increases), local_id: 43 }","value":"usize","parent":null,"children":[],"decl_id":null,"docs":"","sig":null,"attributes":[]}],"impls":[],"refs":[{"kind":"Mod","span":{"file_name":"src/main.rs","byte_start":28,"byte_end":36,"line_start":3,"line_end":3,"column_start":5,"column_end":13},"ref_id":{"krate":17,"index":0}},{"kind":"Type","span":{"file_name":"src/main.rs","byte_start":53,"byte_end":56,"line_start":5,"line_end":5,"column_start":5,"column_end":8},"ref_id":{"krate":1,"index":3016}},{"kind":"Mod","span":{"file_name":"src/main.rs","byte_start":64,"byte_end":66,"line_start":6,"line_end":6,"column_start":5,"column_end":7},"ref_id":{"krate":1,"index":2958}},{"kind":"Type","span":{"file_name":"src/main.rs","byte_start":53,"byte_end":56,"line_start":5,"line_end":5,"column_start":5,"column_end":8},"ref_id":{"krate":1,"index":4357}},{"kind":"Type","span":{"file_name":"src/main.rs","byte_start":78,"byte_end":80,"line_start":7,"line_end":7,"column_start":5,"column_end":7},"ref_id":{"krate":1,"index":4357}},{"kind":"Type","span":{"file_name":"src/main.rs","byte_start":53,"byte_end":56,"line_start":5,"line_end":5,"column_start":5,"column_end":8},"ref_id":{"krate":1,"index":3331}},{"kind":"Type","span":{"file_name":"src/main.rs","byte_start":78,"byte_end":80,"line_start":7,"line_end":7,"column_start":5,"column_end":7},"ref_id":{"krate":1,"index":3331}},{"kind":"Type","span":{"file_name":"src/main.rs","byte_start":53,"byte_end":56,"line_start":5,"line_end":5,"column_start":5,"column_end":8},"ref_id":{"krate":1,"index":3753}},{"kind":"Type","span":{"file_name":"src/main.rs","byte_start":78,"byte_end":80,"line_start":7,"line_end":7,"column_start":5,"column_end":7},"ref_id":{"krate":1,"index":3753}},{"kind":"Type","span":{"file_name":"src/main.rs","byte_start":53,"byte_end":56,"line_start":5,"line_end":5,"column_start":5,"column_end":8},"ref_id":{"krate":1,"index":10197}},{"kind":"Type","span":{"file_name":"src/main.rs","byte_start":78,"byte_end":80,"line_start":7,"line_end":7,"column_start":5,"column_end":7},"ref_id":{"krate":1,"index":10197}},{"kind":"Type","span":{"file_name":"src/main.rs","byte_start":53,"byte_end":56,"line_start":5,"line_end":5,"column_start":5,"column_end":8},"ref_id":{"krate":1,"index":6637}},{"kind":"Mod","span":{"file_name":"src/main.rs","byte_start":126,"byte_end":130,"line_start":8,"line_end":8,"column_start":5,"column_end":9},"ref_id":{"krate":1,"index":6335}},{"kind":"Function","span":{"file_name":"src/main.rs","byte_start":179,"byte_end":182,"line_start":12,"line_end":12,"column_start":26,"column_end":29},"ref_id":{"krate":1,"index":6642}},{"kind":"Type","span":{"file_name":"src/main.rs","byte_start":173,"byte_end":177,"line_start":12,"line_end":12,"column_start":20,"column_end":24},"ref_id":{"krate":1,"index":6637}},{"kind":"Function","span":{"file_name":"src/main.rs","byte_start":256,"byte_end":262,"line_start":13,"line_end":13,"column_start":43,"column_end":49},"ref_id":{"krate":2,"index":8247}},{"kind":"Function","span":{"file_name":"src/main.rs","byte_start":230,"byte_end":245,"line_start":13,"line_end":13,"column_start":17,"column_end":32},"ref_id":{"krate":0,"index":28}},{"kind":"Variable","span":{"file_name":"src/main.rs","byte_start":246,"byte_end":254,"line_start":13,"line_end":13,"column_start":33,"column_end":41},"ref_id":{"krate":0,"index":268435483}},{"kind":"Function","span":{"file_name":"src/main.rs","byte_start":364,"byte_end":385,"line_start":15,"line_end":15,"column_start":18,"column_end":39},"ref_id":{"krate":0,"index":33}},{"kind":"Variable","span":{"file_name":"src/main.rs","byte_start":387,"byte_end":392,"line_start":15,"line_end":15,"column_start":41,"column_end":46},"ref_id":{"krate":0,"index":3355443227}},{"kind":"Function","span":{"file_name":"src/main.rs","byte_start":412,"byte_end":436,"line_start":16,"line_end":16,"column_start":18,"column_end":42},"ref_id":{"krate":0,"index":34}},{"kind":"Variable","span":{"file_name":"src/main.rs","byte_start":442,"byte_end":447,"line_start":16,"line_end":16,"column_start":48,"column_end":53},"ref_id":{"krate":0,"index":3355443227}},{"kind":"Variable","span":{"file_name":"src/main.rs","byte_start":472,"byte_end":478,"line_start":18,"line_end":18,"column_start":22,"column_end":28},"ref_id":{"krate":0,"index":939524123}},{"kind":"Type","span":{"file_name":"src/main.rs","byte_start":518,"byte_end":523,"line_start":21,"line_end":21,"column_start":35,"column_end":40},"ref_id":{"krate":2,"index":2750}},{"kind":"Type","span":{"file_name":"src/main.rs","byte_start":524,"byte_end":528,"line_start":21,"line_end":21,"column_start":41,"column_end":45},"ref_id":{"krate":1,"index":6637}},{"kind":"Type","span":{"file_name":"src/main.rs","byte_start":513,"byte_end":529,"line_start":21,"line_end":21,"column_start":30,"column_end":46},"ref_id":{"krate":0,"index":29}},{"kind":"Type","span":{"file_name":"src/main.rs","byte_start":534,"byte_end":540,"line_start":21,"line_end":21,"column_start":51,"column_end":57},"ref_id":{"krate":2,"index":40079}},{"kind":"Type","span":{"file_name":"src/main.rs","byte_start":541,"byte_end":544,"line_start":21,"line_end":21,"column_start":58,"column_end":61},"ref_id":{"krate":5,"index":6773}},{"kind":"Type","span":{"file_name":"src/main.rs","byte_start":551,"byte_end":556,"line_start":21,"line_end":21,"column_start":68,"column_end":73},"ref_id":{"krate":1,"index":3753}},{"kind":"Function","span":{"file_name":"src/main.rs","byte_start":596,"byte_end":602,"line_start":22,"line_end":22,"column_start":37,"column_end":43},"ref_id":{"krate":2,"index":8247}},{"kind":"Function","span":{"file_name":"src/main.rs","byte_start":581,"byte_end":585,"line_start":22,"line_end":22,"column_start":22,"column_end":26},"ref_id":{"krate":1,"index":3034}},{"kind":"Type","span":{"file_name":"src/main.rs","byte_start":575,"byte_end":579,"line_start":22,"line_end":22,"column_start":16,"column_end":20},"ref_id":{"krate":1,"index":3016}},{"kind":"Variable","span":{"file_name":"src/main.rs","byte_start":586,"byte_end":594,"line_start":22,"line_end":22,"column_start":27,"column_end":35},"ref_id":{"krate":0,"index":1073741852}},{"kind":"Function","span":{"file_name":"src/main.rs","byte_start":645,"byte_end":648,"line_start":23,"line_end":23,"column_start":26,"column_end":29},"ref_id":{"krate":1,"index":3339}},{"kind":"Type","span":{"file_name":"src/main.rs","byte_start":634,"byte_end":643,"line_start":23,"line_end":23,"column_start":15,"column_end":24},"ref_id":{"krate":1,"index":3331}},{"kind":"Variable","span":{"file_name":"src/main.rs","byte_start":649,"byte_end":653,"line_start":23,"line_end":23,"column_start":30,"column_end":34},"ref_id":{"krate":0,"index":1879048220}},{"kind":"Function","span":{"file_name":"src/main.rs","byte_start":782,"byte_end":789,"line_start":26,"line_end":26,"column_start":10,"column_end":17},"ref_id":{"krate":2,"index":7367}},{"kind":"Function","span":{"file_name":"src/main.rs","byte_start":681,"byte_end":684,"line_start":25,"line_end":25,"column_start":10,"column_end":13},"ref_id":{"krate":2,"index":7329}},{"kind":"Function","span":{"file_name":"src/main.rs","byte_start":664,"byte_end":669,"line_start":24,"line_end":24,"column_start":9,"column_end":14},"ref_id":{"krate":1,"index":4364}},{"kind":"Variable","span":{"file_name":"src/main.rs","byte_start":660,"byte_end":663,"line_start":24,"line_end":24,"column_start":5,"column_end":8},"ref_id":{"krate":0,"index":402653212}},{"kind":"Function","span":{"file_name":"src/main.rs","byte_start":697,"byte_end":705,"line_start":25,"line_end":25,"column_start":26,"column_end":34},"ref_id":{"krate":2,"index":8211}},{"kind":"Variable","span":{"file_name":"src/main.rs","byte_start":692,"byte_end":696,"line_start":25,"line_end":25,"column_start":21,"column_end":25},"ref_id":{"krate":0,"index":2214592540}},{"kind":"Function","span":{"file_name":"src/main.rs","byte_start":720,"byte_end":727,"line_start":25,"line_end":25,"column_start":49,"column_end":56},"ref_id":{"krate":2,"index":8204}},{"kind":"Function","span":{"file_name":"src/main.rs","byte_start":712,"byte_end":717,"line_start":25,"line_end":25,"column_start":41,"column_end":46},"ref_id":{"krate":2,"index":11876}},{"kind":"Variable","span":{"file_name":"src/main.rs","byte_start":710,"byte_end":711,"line_start":25,"line_end":25,"column_start":39,"column_end":40},"ref_id":{"krate":0,"index":1677721628}},{"kind":"Function","span":{"file_name":"src/main.rs","byte_start":739,"byte_end":742,"line_start":25,"line_end":25,"column_start":68,"column_end":71},"ref_id":{"krate":1,"index":3776}},{"kind":"Type","span":{"file_name":"src/main.rs","byte_start":732,"byte_end":737,"line_start":25,"line_end":25,"column_start":61,"column_end":66},"ref_id":{"krate":1,"index":3753}},{"kind":"Type","span":{"file_name":"src/main.rs","byte_start":754,"byte_end":765,"line_start":25,"line_end":25,"column_start":83,"column_end":94},"ref_id":{"krate":1,"index":10222}},{"kind":"Type","span":{"file_name":"src/main.rs","byte_start":743,"byte_end":752,"line_start":25,"line_end":25,"column_start":72,"column_end":81},"ref_id":{"krate":1,"index":10197}},{"kind":"Variable","span":{"file_name":"src/main.rs","byte_start":767,"byte_end":768,"line_start":25,"line_end":25,"column_start":96,"column_end":97},"ref_id":{"krate":0,"index":3019898908}},{"kind":"Variable","span":{"file_name":"src/main.rs","byte_start":888,"byte_end":889,"line_start":32,"line_end":32,"column_start":14,"column_end":15},"ref_id":{"krate":2,"index":38530}},{"kind":"Variable","span":{"file_name":"src/main.rs","byte_start":891,"byte_end":903,"line_start":32,"line_end":32,"column_start":17,"column_end":29},"ref_id":{"krate":2,"index":38531}},{"kind":"Function","span":{"file_name":"src/main.rs","byte_start":898,"byte_end":901,"line_start":32,"line_end":32,"column_start":24,"column_end":27},"ref_id":{"krate":2,"index":10714}},{"kind":"Variable","span":{"file_name":"src/main.rs","byte_start":891,"byte_end":897,"line_start":32,"line_end":32,"column_start":17,"column_end":23},"ref_id":{"krate":0,"index":1073741857}},{"kind":"Variable","span":{"file_name":"src/main.rs","byte_start":883,"byte_end":884,"line_start":32,"line_end":32,"column_start":9,"column_end":10},"ref_id":{"krate":2,"index":39953}},{"kind":"Variable","span":{"file_name":"src/main.rs","byte_start":917,"byte_end":923,"line_start":33,"line_end":33,"column_start":12,"column_end":18},"ref_id":{"krate":0,"index":1073741857}},{"kind":"Variable","span":{"file_name":"src/main.rs","byte_start":924,"byte_end":925,"line_start":33,"line_end":33,"column_start":19,"column_end":20},"ref_id":{"krate":0,"index":2751463457}},{"kind":"Variable","span":{"file_name":"src/main.rs","byte_start":929,"byte_end":935,"line_start":33,"line_end":33,"column_start":24,"column_end":30},"ref_id":{"krate":0,"index":1073741857}},{"kind":"Variable","span":{"file_name":"src/main.rs","byte_start":936,"byte_end":937,"line_start":33,"line_end":33,"column_start":31,"column_end":32},"ref_id":{"krate":0,"index":2751463457}},{"kind":"Variable","span":{"file_name":"src/main.rs","byte_start":955,"byte_end":962,"line_start":34,"line_end":34,"column_start":13,"column_end":20},"ref_id":{"krate":0,"index":2684354593}},{"kind":"Variable","span":{"file_name":"src/main.rs","byte_start":997,"byte_end":1004,"line_start":38,"line_end":38,"column_start":12,"column_end":19},"ref_id":{"krate":0,"index":2684354593}},{"kind":"Function","span":{"file_name":"src/main.rs","byte_start":1089,"byte_end":1092,"line_start":42,"line_end":42,"column_start":24,"column_end":27},"ref_id":{"krate":5,"index":6780}},{"kind":"Type","span":{"file_name":"src/main.rs","byte_start":1084,"byte_end":1087,"line_start":42,"line_end":42,"column_start":19,"column_end":22},"ref_id":{"krate":5,"index":6773}},{"kind":"Variable","span":{"file_name":"src/main.rs","byte_start":1110,"byte_end":1111,"line_start":44,"line_end":44,"column_start":14,"column_end":15},"ref_id":{"krate":2,"index":38530}},{"kind":"Variable","span":{"file_name":"src/main.rs","byte_start":1113,"byte_end":1127,"line_start":44,"line_end":44,"column_start":17,"column_end":31},"ref_id":{"krate":2,"index":38531}},{"kind":"Function","span":{"file_name":"src/main.rs","byte_start":1120,"byte_end":1123,"line_start":44,"line_end":44,"column_start":24,"column_end":27},"ref_id":{"krate":2,"index":10714}},{"kind":"Variable","span":{"file_name":"src/main.rs","byte_start":1113,"byte_end":1119,"line_start":44,"line_end":44,"column_start":17,"column_end":23},"ref_id":{"krate":0,"index":1073741858}},{"kind":"Variable","span":{"file_name":"src/main.rs","byte_start":1105,"byte_end":1106,"line_start":44,"line_end":44,"column_start":9,"column_end":10},"ref_id":{"krate":2,"index":39953}},{"kind":"Function","span":{"file_name":"src/main.rs","byte_start":1142,"byte_end":1146,"line_start":45,"line_end":45,"column_start":13,"column_end":17},"ref_id":{"krate":5,"index":6844}},{"kind":"Variable","span":{"file_name":"src/main.rs","byte_start":1138,"byte_end":1141,"line_start":45,"line_end":45,"column_start":9,"column_end":12},"ref_id":{"krate":0,"index":2415919138}},{"kind":"Variable","span":{"file_name":"src/main.rs","byte_start":1147,"byte_end":1153,"line_start":45,"line_end":45,"column_start":18,"column_end":24},"ref_id":{"krate":0,"index":1073741858}},{"kind":"Variable","span":{"file_name":"src/main.rs","byte_start":1154,"byte_end":1155,"line_start":45,"line_end":45,"column_start":25,"column_end":26},"ref_id":{"krate":0,"index":3556769826}},{"kind":"Variable","span":{"file_name":"src/main.rs","byte_start":1159,"byte_end":1165,"line_start":45,"line_end":45,"column_start":30,"column_end":36},"ref_id":{"krate":0,"index":1073741858}},{"kind":"Variable","span":{"file_name":"src/main.rs","byte_start":1166,"byte_end":1167,"line_start":45,"line_end":45,"column_start":37,"column_end":38},"ref_id":{"krate":0,"index":3556769826}},{"kind":"Variable","span":{"file_name":"src/main.rs","byte_start":1173,"byte_end":1179,"line_start":45,"line_end":45,"column_start":44,"column_end":50},"ref_id":{"krate":0,"index":1073741858}},{"kind":"Variable","span":{"file_name":"src/main.rs","byte_start":1180,"byte_end":1181,"line_start":45,"line_end":45,"column_start":51,"column_end":52},"ref_id":{"krate":0,"index":3556769826}},{"kind":"Function","span":{"file_name":"src/main.rs","byte_start":1205,"byte_end":1226,"line_start":48,"line_end":48,"column_start":12,"column_end":33},"ref_id":{"krate":0,"index":33}},{"kind":"Variable","span":{"file_name":"src/main.rs","byte_start":1232,"byte_end":1235,"line_start":48,"line_end":48,"column_start":39,"column_end":42},"ref_id":{"krate":0,"index":2415919138}}],"macro_refs":[],"relations":[]}